html2pdf4doc/__init__.py
html2pdf4doc/main.py
html2pdf4doc/main_fuzzer.py
html2pdf4doc/html2pdf4doc_js/html2pdf4doc.min.js
html2pdf4doc-0.0.31.dist-info/METADATA
html2pdf4doc-0.0.31.dist-info/WHEEL
html2pdf4doc-0.0.31.dist-info/entry_points.txt
html2pdf4doc-0.0.31.dist-info/licenses/LICENSE
html2pdf4doc-0.0.31.dist-info/RECORD
